{
  "model": "lumi.light.acn037",
  "device_name": "轨道灯 V1",
  "model_type": 3,
  "resources": {
    "8.0.2009": {
      "name": "开关",
      "description": "0:关或按下；1：开或释放，只读",
      "access": 7,
      "value": ""
    },
    "8.0.2045": {
      "name": "设备在线离线状态",
      "description": "0 离线  1 在线",
      "access": 7,
      "value": "1"
    },
    "1.12.85": {
      "name": "设置灯关的渐变时间",
      "description": "1ms",
      "access": 7,
      "value": "15"
    },
    "1.9.85": {
      "name": "设置色温",
      "description": "色温值,取值为微倒度，即1000000/色温度。比如5000K，则色温值为1000000/5000=200.色温度范围2700K~6000K",
      "access": 7,
      "value": "250"
    },
    "1.9.65": {
      "name": "最暖色温",
      "description": "色温值,取值为微倒度，即1000000/色温度。比如5000K，则色温值为1000000/5000=200.色温度范围2700K~6000K",
      "access": 3,
      "value": "370.000000"
    },
    "1.9.69": {
      "name": "最冷色温",
      "description": "色温值,取值为微倒度，即1000000/色温度。比如5000K，则色温值为1000000/5000=200.色温度范围2700K~6000K",
      "access": 3,
      "value": "166.000000"
    },
    "4.17.85": {
      "name": "是否进入动态情景模式",
      "description": "Light work mode:\r\n0x00:正常模式\r\n0x01:动态情景模式\r\n\r\n心跳上报",
      "access": 3,
      "value": "0"
    },
    "0.12.85": {
      "name": "负载功率",
      "description": "负载功率，单位是瓦 W。每个心跳时上报，或变化超过±5W或±3%，则上报，只读",
      "access": 3,
      "value": "0"
    },
    "1.7.69": {
      "name": "最低亮度",
      "description": "设置灯光实际调节的最小值",
      "access": 7,
      "value": "1"
    },
    "1.7.65": {
      "name": "最高亮度",
      "description": "设置灯光实际调节的最大值",
      "access": 7,
      "value": "100"
    },
    "1.7.85": {
      "name": "设置亮度",
      "description": "设置灯亮度，范围：1~100%",
      "access": 7,
      "value": "20"
    },
    "4.1.85": {
      "name": "开关状态",
      "description": "开关状态，0:关闭，1:打开，2：toggle",
      "access": 7,
      "value": "1"
    },
    "8.0.2221": {
      "name": "情景模式配置信息",
      "description": "下发情景模式的配置信息，格式待定",
      "access": 7,
      "value": ""
    },
    "8.0.2259": {
      "name": "通电状态设置",
      "description": "通电后默认状态\n0：通电后开灯\n1：保持断电前的状态（默认）\n2：通电后关灯\n3：开关状态反向",
      "access": 7,
      "value": "1"
    }
  },
  "fetched_at": "2026-05-03T00:28:01.968641"
}